MANIFEST.in
README.rst
requirements.txt
setup.py
django_passaporte_web.egg-info/PKG-INFO
django_passaporte_web.egg-info/SOURCES.txt
django_passaporte_web.egg-info/dependency_links.txt
django_passaporte_web.egg-info/requires.txt
django_passaporte_web.egg-info/top_level.txt
identity_client/__init__.py
identity_client/backend.py
identity_client/client_api_methods.py
identity_client/decorators.py
identity_client/forms.py
identity_client/handlers.py
identity_client/middleware.py
identity_client/models.py
identity_client/processors.py
identity_client/shortcuts.py
identity_client/signals.py
identity_client/timezones.py
identity_client/urls.py
identity_client/utils.py
identity_client/views.py
identity_client/django_db/__init__.py
identity_client/django_db/models.py
identity_client/django_db/settings.py
identity_client/migrations/0001_initial.py
identity_client/migrations/0002_auto_20141029_1259.py
identity_client/migrations/__init__.py
identity_client/mongoengine_db/__init__.py
identity_client/mongoengine_db/models.py
identity_client/mongoengine_db/mongodb_test.py
identity_client/mongoengine_db/settings.py
identity_client/south_migrations/0001_initial.py
identity_client/south_migrations/0002_auto__add_accountmember__add_serviceaccount.py
identity_client/south_migrations/0003_auto__del_unique_identity_email.py
identity_client/south_migrations/__init__.py
identity_client/sso/__init__.py
identity_client/sso/client.py
identity_client/sso/decorators.py
identity_client/sso/urls.py
identity_client/sso/views.py
identity_client/templates/accounts_list.html
identity_client/templates/login.html
identity_client/templates/logout.html
identity_client/templates/registration_form.html
identity_client/templates/user_data.html
identity_client/templatetags/__init__.py
identity_client/templatetags/gravatars.py
identity_client/tests/__init__.py
identity_client/tests/helpers.py
identity_client/tests/mock_helpers.py
identity_client/tests/test_backend.py
identity_client/tests/test_client_api_methods.py
identity_client/tests/test_client_views.py
identity_client/tests/test_decorators.py
identity_client/tests/test_forms.py
identity_client/tests/test_models.py
identity_client/tests/test_p3p_middleware.py
