Metadata-Version: 1.1
Name: django-passaporte-web
Version: 1.2.7
Summary: Django client app for Passaporte Web.
Home-page: http://github.com/myfreecomm/django-passaporte-web
Author: vitormazzi
Author-email: vitormazzi@gmail.com
License: Apache 2.0
Keywords: django python passaporteweb
Platform: UNKNOWN
Classifier: Framework :: Django
Classifier: Intended Audience :: Developers
Classifier: License :: OSI Approved :: Apache Software License
Classifier: Operating System :: OS Independent
Classifier: Topic :: Software Development
